[
    {
        "slug": "slumber-party-panic",
        "name": "Slumber Party Panic",
        "description": "Finn and Jake must save Princess Bubblegum from an impending zombie attack.",
        "image": "/assets/images/episodes/slumber-party-panic.webp",
        "thumbnail": "/assets/images/episodes/slumber-party-panic-thumbnail.webp",
        "release": "2010-04-05",
        "episode": "S01E01",
        "character_slugs": ["finn", "jake"]
    },
    {
        "slug": "trouble-in-lumpy-space",
        "name": "Trouble in Lumpy Space",
        "description": "Finn and Jake venture into Lumpy Space to cure the Lumps from Jake's bite.",
        "image": "/assets/images/episodes/trouble-in-lumpy-space.webp",
        "thumbnail": "/assets/images/episodes/trouble-in-lumpy-space-thumbnail.webp",
        "release": "2010-04-12",
        "episode": "S01E02",
        "character_slugs": ["finn", "jake"]
    },
    {
        "slug": "prisoners-of-love",
        "name": "Prisoners of Love",
        "description": "Finn and Jake go on a mission to rescue kidnapped princesses from the Ice King.",
        "image": "/assets/images/episodes/prisoners-of-love.webp",
        "thumbnail": "/assets/images/episodes/prisoners-of-love-thumbnail.webp",
        "release": "2010-04-19",
        "episode": "S01E03",
        "character_slugs": ["finn"]
    },
    {
        "slug": "tree-trunks",
        "name": "Tree Trunks",
        "description": "Finn and Jake go on a quest with Tree Trunks to find the legendary Crystal Gem Apple.",
        "image": "/assets/images/episodes/tree-trunks.webp",
        "thumbnail": "/assets/images/episodes/tree-trunks-thumbnail.webp",
        "release": "2010-04-26",
        "episode": "S01E04",
        "character_slugs": ["jake"]
    }
]
